{
    "mapping": {
        "rhn.system.sid": "None",
        "rhn.system.profile_name": "None",
        "rhn.system.description": "None",
        "rhn.system.hostname": "fqdn",
        "rhn.system.ip_address": "ipaddress",
        "rhn.system.custom_info(key_name)": "None",
        "rhn.system.net_interface.ip_address(eth_device)": "ipaddress_{NETWORK INTERFACE}",
        "rhn.system.net_interface.netmask(eth_device)": "netmask_{NETWORK INTERFACE}",
        "rhn.system.net_interface.broadcast(eth_device)": "None",
        "rhn.system.net_interface.hardware_address(eth_device)": "macaddress_{NETWORK INTERFACE}",
        "rhn.system.net_interface.driver_module(eth_device)": "None"
    }
}